pubmlstdownload/__init__.c
pubmlstdownload/__init__.py
pubmlstdownload/pubmlst_download.c
pubmlstdownload/schemes.json
pubmlstdownload/__init__.cpython-310-darwin.so
pubmlstdownload/pubmlst_download.cpython-310-darwin.so
pubmlstdownload-0.1.0.dist-info/METADATA
pubmlstdownload-0.1.0.dist-info/WHEEL
pubmlstdownload-0.1.0.dist-info/entry_points.txt
pubmlstdownload-0.1.0.dist-info/RECORD
