Metadata-Version: 2.4
Name: pubmlstdownload
Version: 0.1.0
Summary: A high-performance Python tool for downloading MLST (Multilocus Sequence Typing) and cgMLST (core genome MLST) schemes and allele sequences from the [PubMLST](https://pubmlst.org/) database using their RESTful API.
Project-URL: Homepage, https://github.com/hbucqp/pubmlstdownload
Project-URL: Repository, https://github.com/hbucqp/pubmlstdownload
Project-URL: Documentation, https://github.com/hbucqp/pubmlstdownload#readme
Project-URL: Issues, https://github.com/hbucqp/pubmlstdownload/issues
Author-email: Qingpo Cui <cqp@cau.edu.cn>
License-Expression: MIT
Keywords: MLST,PubMLST,bacterial-genomics,bioinformatics,cgMLST,genomics,sequence-typing
Classifier: Development Status :: 4 - Beta
Classifier: Intended Audience :: Science/Research
Classifier: Operating System :: OS Independent
Classifier: Programming Language :: Python :: 3
Classifier: Programming Language :: Python :: 3.10
Classifier: Programming Language :: Python :: 3.11
Classifier: Programming Language :: Python :: 3.12
Classifier: Topic :: Scientific/Engineering :: Bio-Informatics
Requires-Python: >=3.10
Requires-Dist: requests>=2.32.5
